commons/__init__.py
commons/admin.py
commons/apps.py
commons/managers.py
commons/models.py
commons/permissions.py
commons/urls.py
commons/views.py
commons/fixtures/group-model.json
commons/fixtures/permission-model.json
commons/fixtures/user-model.json
commons/migrations/0001_initial.py
commons/migrations/__init__.py
commons/templates/commons/base_module.html
commons/templates/commons/menu.html
commons/templates/commons/person_detail.html
commons/templatetags/__init__.py
commons/templatetags/formats.py
corgy_common/__init__.py
corgy_common/admin.py
corgy_common/apps.py
corgy_common/models.py
corgy_common/urls.py
corgy_common/views.py
corgy_common/management/__init__.py
corgy_common/management/commands/__init__.py
corgy_common/management/commands/customize.py
corgy_common/migrations/0001_initial.py
corgy_common/migrations/0002_delete_account.py
corgy_common/migrations/__init__.py
corgy_common/templates/corgy_common/base_module.html
corgy_common/templates/corgy_common/menu.html
corgy_erp/__init__.py
corgy_erp/asgi.py
corgy_erp/backend.py
corgy_erp/celery.py
corgy_erp/feeds.py
corgy_erp/roles.py
corgy_erp/settings.py
corgy_erp/sitemaps.py
corgy_erp/tests.py
corgy_erp/urls.py
corgy_erp/version.py
corgy_erp/views.py
corgy_erp/wsgi.py
corgy_erp/locale/hu/LC_MESSAGES/django.mo
corgy_erp/locale/hu/LC_MESSAGES/django.po
corgy_erp/templates/admin/base_site.html
corgy_erp/templates/admin/index.html
corgy_erp/templates/flatpages/default.html
corgy_erp/templates/material/frontend/base.html
corgy_erp/templates/material/frontend/base_lockscreen.html
corgy_erp/templates/material/frontend/base_module.html
corgy_erp/templates/material/frontend/base_site.html
corgy_erp/templatetags/__init__.py
corgy_erp/templatetags/verbose.py
corgy_erp/templatetags/version.py
corgy_erp-5.1.2.data/scripts/manage.py
customers/__init__.py
customers/admin.py
customers/apps.py
customers/flows.py
customers/forms.py
customers/managers.py
customers/models.py
customers/signals.py
customers/urls.py
corgy_erp-5.1.2.dist-info/LICENSE
corgy_erp-5.1.2.dist-info/METADATA
corgy_erp-5.1.2.dist-info/WHEEL
corgy_erp-5.1.2.dist-info/top_level.txt
corgy_erp-5.1.2.dist-info/RECORD
